fairsense/data_management/__init__.py
fairsense/data_management/factory.py
fairsense/data_management/processing.py
fairsense/indices/__init__.py
fairsense/indices/confidence_intervals.py
fairsense/indices/cvm.py
fairsense/indices/sobol.py
fairsense/indices/standard_metrics.py
fairsense/utils/__init__.py
fairsense/utils/dataclasses.py
fairsense/utils/fairness_objective.py
fairsense/visualization/__init__.py
fairsense/visualization/plots.py
fairsense/visualization/text.py
fairsense-0.0.1.dist-info/LICENSE
fairsense-0.0.1.dist-info/METADATA
fairsense-0.0.1.dist-info/WHEEL
fairsense-0.0.1.dist-info/top_level.txt
fairsense-0.0.1.dist-info/RECORD
