Metadata-Version: 2.1
Name: fairsense
Version: 0.0.1
Summary: This library allow to compute global sensitivity indices in the context of fairness measurements.
Home-page: https://github.com/deel-ai/FairSense
Author: Thibaut BOISSIN, Alexandre LANGLADE
Author-email: thibaut.boissin@irt-saintexupery.com, alexandre.langlade@irt-saintexupery.com
License: MIT
Classifier: Programming Language :: Python :: 3
Classifier: Programming Language :: Python :: 3.6
Classifier: Programming Language :: Python :: 3.7
Classifier: Programming Language :: Python :: 3.8
Classifier: License :: OSI Approved :: MIT License
Classifier: Operating System :: OS Independent
Requires-Python: >=3.6
License-File: LICENSE
Requires-Dist: numpy
Requires-Dist: pandas
Requires-Dist: matplotlib
Requires-Dist: scikit-learn
Requires-Dist: seaborn
Requires-Dist: tqdm
Provides-Extra: all
Requires-Dist: numpy ; extra == 'all'
Requires-Dist: pandas ; extra == 'all'
Requires-Dist: matplotlib ; extra == 'all'
Requires-Dist: scikit-learn ; extra == 'all'
Requires-Dist: seaborn ; extra == 'all'
Requires-Dist: tqdm ; extra == 'all'
Requires-Dist: setuptools ; extra == 'all'
Requires-Dist: pre-commit ; extra == 'all'
Requires-Dist: tox ; extra == 'all'
Requires-Dist: black ; extra == 'all'
Requires-Dist: flake8 ; extra == 'all'
Requires-Dist: flake8-black ; extra == 'all'
Requires-Dist: pytest ; extra == 'all'
Requires-Dist: pylint ; extra == 'all'
Requires-Dist: bump2version ; extra == 'all'
Requires-Dist: mkdocs ; extra == 'all'
Requires-Dist: mkdocs-material ; extra == 'all'
Requires-Dist: mkdocstrings[python] ; extra == 'all'
Requires-Dist: mknotebooks ; extra == 'all'
Requires-Dist: ipython ; extra == 'all'
Provides-Extra: dev
Requires-Dist: setuptools ; extra == 'dev'
Requires-Dist: pre-commit ; extra == 'dev'
Requires-Dist: tox ; extra == 'dev'
Requires-Dist: black ; extra == 'dev'
Requires-Dist: flake8 ; extra == 'dev'
Requires-Dist: flake8-black ; extra == 'dev'
Requires-Dist: pytest ; extra == 'dev'
Requires-Dist: pylint ; extra == 'dev'
Requires-Dist: bump2version ; extra == 'dev'
Provides-Extra: docs
Requires-Dist: mkdocs ; extra == 'docs'
Requires-Dist: mkdocs-material ; extra == 'docs'
Requires-Dist: mkdocstrings[python] ; extra == 'docs'
Requires-Dist: mknotebooks ; extra == 'docs'
Requires-Dist: ipython ; extra == 'docs'
